{
   "type":"BLFlowSolverIncompDRL",

   "mesh_h5_file_path":"",
   "mesh_h5_file_name":"bl_les",

   "results_h5_file_path":"",
   "results_h5_file_name":"results",

   "final_istep":9000001,

   "save_logFile_first":1,
   "save_logFile_step":10,

   "save_resultsFile_first":1,
   "save_resultsFile_step":1000,

   "save_restartFile_first":1,
   "save_restartFile_step":25000,

   "continue_oldLogs":false,

   "saveAvgFile":false,
   "loadAvgFile":false,
   "initial_avgTime":5000,

   "saveSurfaceResults":false,

   "flag_les":1,

   "maxIter":30,
   "tol":1e-2,

   "cfl_conv":0.95,

   "U0":1.0,
   "d0":1.0,
   "rho0":1.0,
   "Red0":450,

   "vmax_SB":0.4,
   "xc_SB":306.640625,
   "eps_SB":110.485435,
   "psi_SB":0.95,

   "xmin_tripping":-40.0,
   "lx_tripping":2.5,
   "ly_tripping":2.5,

   "fileControlName": "rectangleControl.txt",

   "spanLength":125.0,
   "n_pseudo_envs":3,

   "have_witness":true,
   "witness_inp_file_name":"witness.txt",
   "witness_h5_file_name":"resultwit.h5",
   "leapwit":10000001,
   "leapwitsave":1,
   "nwit":216,
   "wit_save": false,
   "wit_save_u_i":false,
   "wit_save_pr":false,
   "wit_save_rho":false,
   "continue_witness":false,

   "bouCodes":
   [
      {"id":1, "bc_type":"bc_type_unsteady_inlet"},
      {"id":2, "bc_type":"bc_type_unsteady_inlet"},
      {"id":3, "bc_type":"bc_type_unsteady_inlet"},
      {"id":4, "bc_type":"bc_type_far_field_SB"},
      {"id":5, "bc_type":"bc_type_far_field"},
      {"id":6, "bc_type":"bc_type_outlet_incomp"},
   ],

   "buffer":
   [
      {"type":"east","min":950,"size":50},
      {"type":"west","min":-50,"size":50},
   ]
}
